orthanc_tools/__init__.py
orthanc_tools/dicom_migrator.py
orthanc_tools/hl7_worklist_server_for_orthanc.py
orthanc_tools/ids_migrator.py
orthanc_tools/label_modifier.py
orthanc_tools/orthanc_cleaner.py
orthanc_tools/orthanc_cloner.py
orthanc_tools/orthanc_comparator.py
orthanc_tools/orthanc_downloader.py
orthanc_tools/orthanc_folder_importer.py
orthanc_tools/orthanc_forwarder.py
orthanc_tools/orthanc_monitor.py
orthanc_tools/orthanc_replicator.py
orthanc_tools/orthanc_syncher.py
orthanc_tools/orthanc_test_db_populator.py
orthanc_tools/orthanc_uploader.py
orthanc_tools/orthanc_warmer.py
orthanc_tools/pacs_migrator.py
orthanc_tools/postgres_dumper.py
orthanc_tools/helpers/__init__.py
orthanc_tools/helpers/old_files_deleter.py
orthanc_tools/helpers/scheduler.py
orthanc_tools/helpers/time_out.py
orthanc_tools/helpers/timer.py
orthanc_tools/hl7Lib/__init__.py
orthanc_tools/hl7Lib/hl7.py
orthanc_tools/hl7Lib/hl7_client.py
orthanc_tools/hl7Lib/hl7_dicom_worklist_builder.py
orthanc_tools/hl7Lib/hl7_error.py
orthanc_tools/hl7Lib/hl7_folder_monitor.py
orthanc_tools/hl7Lib/hl7_message_parser.py
orthanc_tools/hl7Lib/hl7_message_validator.py
orthanc_tools/hl7Lib/hl7_orm_worklist_msg_handler.py
orthanc_tools/hl7Lib/hl7_oru_report_msg_handler.py
orthanc_tools/hl7Lib/hl7_report_parser.py
orthanc_tools/hl7Lib/hl7_report_series_builder.py
orthanc_tools/hl7Lib/hl7_server.py
orthanc_tools/hl7Lib/hl7_worklist_parser.py
orthanc_tools/hl7Lib/hl7_worklist_parser_assistovet.py
orthanc_tools/hl7Lib/hl7_worklist_parser_vetera.py
orthanc_tools-0.17.15.dist-info/licenses/LICENSE.txt
orthanc_tools-0.17.15.dist-info/METADATA
orthanc_tools-0.17.15.dist-info/WHEEL
orthanc_tools-0.17.15.dist-info/top_level.txt
orthanc_tools-0.17.15.dist-info/RECORD
